tinyff/__init__.py
tinyff/_version.py
tinyff/analysis.py
tinyff/atomsmithy.py
tinyff/forcefield.py
tinyff/neighborlist.py
tinyff/pairwise.py
tinyff/trajectory.py
tinyff/utils.py
tinyff-2.1.0.dist-info/licenses/LICENSE.txt
tinyff-2.1.0.dist-info/METADATA
tinyff-2.1.0.dist-info/WHEEL
tinyff-2.1.0.dist-info/top_level.txt
tinyff-2.1.0.dist-info/RECORD
