Metadata-Version: 2.4
Name: TinyFF
Version: 2.1.0
Summary: Minimalistic Force Field evaluator.
Author-email: Toon Verstraelen <toon.verstraelen@ugent.be>
License-Expression: GPL-3.0-or-later
Project-URL: Issues, https://github.com/molmod/tinyff/issues
Project-URL: Source, https://github.com/molmod/tinyff/
Project-URL: Changelog, https://github.com/molmod/tinyff/blob/main/CHANGELOG.md
Classifier: Environment :: Console
Classifier: Intended Audience :: Education
Classifier: Operating System :: POSIX
Classifier: Operating System :: MacOS
Classifier: Programming Language :: Python :: 3
Classifier: Topic :: Scientific/Engineering
Classifier: Topic :: Education :: Computer Aided Instruction (CAI)
Requires-Python: >=3.11
License-File: LICENSE.txt
Requires-Dist: attrs>=25.3.0
Requires-Dist: npy-append-array>=0.9.19
Requires-Dist: numpy>=2.3.1
Requires-Dist: scipy>=1.16.0
Provides-Extra: dev
Requires-Dist: pytest; extra == "dev"
Requires-Dist: pytest-cov; extra == "dev"
Requires-Dist: numdifftools>=0.9.41; extra == "dev"
Dynamic: license-file
